{
	"format_version": "1.9.0",
	"credit": "Made with Blockbench",
	"parent": "minecraft:block/block",
	"textures": {
		"4": "cuppasuselessfeatures:block/glistering_melon_top",
		"6": "cuppasuselessfeatures:block/glistering_melon_side",
		"particle": "cuppasuselessfeatures:block/glistering_melon_side"
	},
	"elements": [
		{
			"from": [0, 0, 0],
			"to": [16, 16, 16],
			"faces": {
				"north": {"uv": [0, 0, 16, 16], "texture": "#6"},
				"east": {"uv": [0, 0, 16, 16], "texture": "#6"},
				"south": {"uv": [0, 0, 16, 16], "texture": "#6"},
				"west": {"uv": [0, 0, 16, 16], "texture": "#6"},
				"up": {"uv": [0, 0, 16, 16], "texture": "#4"},
				"down": {"uv": [0, 0, 16, 16], "texture": "#4"}
			}
		}
	]
}